pulsecot/VERSION
pulsecot/__init__.py
pulsecot/classes.py
pulsecot/commands.py
pulsecot/constants.py
pulsecot/functions.py
pulsecot/gnu.py
pulsecot/data/call_types.json
pulsecot-3.0.6.dist-info/licenses/LICENSE
pulsecot-3.0.6.dist-info/METADATA
pulsecot-3.0.6.dist-info/WHEEL
pulsecot-3.0.6.dist-info/entry_points.txt
pulsecot-3.0.6.dist-info/top_level.txt
pulsecot-3.0.6.dist-info/RECORD
