Metadata-Version: 2.4
Name: pulsecot
Version: 3.0.6
Summary: PulsePoint to TAK Gateway
Home-page: https://github.com/snstac/pulsecot
Maintainer: Greg Albrecht <oss@undef.net>
Maintainer-email: oss@undef.net
License: Apache 2.0
Project-URL: CI: GitHub Actions, https://github.com/snstac/pulsecot/actions
Project-URL: GitHub: issues, https://github.com/snstac/pulsecot/issues
Project-URL: GitHub: repo, https://github.com/snstac/pulsecot
Keywords: Cursor on Target,CoT,ATAK,TAK,WinTAK,TAK,TAK Server,PulsePoint
Classifier: License :: OSI Approved :: Apache Software License
Classifier: Intended Audience :: Developers
Classifier: Programming Language :: Python
Classifier: Programming Language :: Python :: 3
Classifier: Development Status :: 5 - Production/Stable
Classifier: Environment :: Console
Classifier: Operating System :: OS Independent
Requires-Python: <4,>=3.7
License-File: LICENSE
Requires-Dist: pytak>=5.4.0
Requires-Dist: aiohttp<4.0.0
Requires-Dist: cryptography>=3.4.7
Requires-Dist: importlib_resources; python_version < "3.9"
Provides-Extra: test
Requires-Dist: pytest-asyncio; extra == "test"
Requires-Dist: pytest-cov; extra == "test"
Requires-Dist: pylint; extra == "test"
Requires-Dist: flake8; extra == "test"
Requires-Dist: black; extra == "test"
Dynamic: license-file
